{
    "f0fb7554-635c-435f-9a84-486a3e209120": {
        "id": "f0fb7554-635c-435f-9a84-486a3e209120",
        "name": "Google Search",
        "keyword": "g",
        "cmd": "https://google.com/search?q=%s",
        "icon": "/usr/share/ulauncher/media/google-search-icon.png",
        "is_default_search": true,
        "run_without_argument": false,
        "added": 1705772490.5822132
    },
    "34b64f7d-2847-4985-a6af-a6aa4b128df1": {
        "id": "34b64f7d-2847-4985-a6af-a6aa4b128df1",
        "name": "Stack Overflow",
        "keyword": "so",
        "cmd": "https://stackoverflow.com/search?q=%s",
        "icon": "/usr/share/ulauncher/media/stackoverflow-icon.svg",
        "is_default_search": true,
        "run_without_argument": false,
        "added": 1705772490.582281
    },
    "73382622-f41b-4059-bd45-da39a2e9cd9d": {
        "id": "73382622-f41b-4059-bd45-da39a2e9cd9d",
        "name": "Wikipedia",
        "keyword": "wiki",
        "cmd": "https://en.wikipedia.org/wiki/%s",
        "icon": "/usr/share/ulauncher/media/wikipedia-icon.png",
        "is_default_search": true,
        "run_without_argument": false,
        "added": 1705772490.5823314
    }
}